igl_kiosk/__init__.py
igl_kiosk/core/__init__.py
igl_kiosk/core/browser.py
igl_kiosk/core/url_injector.py
igl_kiosk/main.py
igl_kiosk/ui/__init__.py
igl_kiosk/ui/main_window.py
igl_kiosk/ui/templates.py
igl_kiosk/utils/__init__.py
igl_kiosk/utils/shortcuts.py
igl_kiosk-0.0.3.dist-info/METADATA
igl_kiosk-0.0.3.dist-info/WHEEL
igl_kiosk-0.0.3.dist-info/entry_points.txt
igl_kiosk-0.0.3.dist-info/RECORD
