Metadata-Version: 2.1
Name: igl-kiosk
Version: 0.0.3
Summary: The kioks application for IGL-Informer based on pyqt6 for embedded.
License: GPL-3.0
Author: Maximilian Erkens
Author-email: max@max-erkens.de
Requires-Python: >=3.10
Classifier: License :: OSI Approved :: GNU General Public License v3 (GPLv3)
Classifier: Programming Language :: Python :: 3
Classifier: Programming Language :: Python :: 3.10
Classifier: Programming Language :: Python :: 3.11
Classifier: Programming Language :: Python :: 3.12
Requires-Dist: pyqt6 (>=6.4.0,<7.0.0)
Requires-Dist: pyqt6-webengine (>=6.4.0,<7.0.0)
